odoo/addons/crm_won_restrict_per_stage/README.rst
odoo/addons/crm_won_restrict_per_stage/__init__.py
odoo/addons/crm_won_restrict_per_stage/__manifest__.py
odoo/addons/crm_won_restrict_per_stage/i18n/crm_won_restrict_per_stage.pot
odoo/addons/crm_won_restrict_per_stage/i18n/es.po
odoo/addons/crm_won_restrict_per_stage/i18n/it.po
odoo/addons/crm_won_restrict_per_stage/i18n/pt_BR.po
odoo/addons/crm_won_restrict_per_stage/models/__init__.py
odoo/addons/crm_won_restrict_per_stage/models/crm_lead.py
odoo/addons/crm_won_restrict_per_stage/models/crm_stage.py
odoo/addons/crm_won_restrict_per_stage/readme/CONFIGURE.md
odoo/addons/crm_won_restrict_per_stage/readme/CONTRIBUTORS.md
odoo/addons/crm_won_restrict_per_stage/readme/DESCRIPTION.md
odoo/addons/crm_won_restrict_per_stage/static/description/icon.png
odoo/addons/crm_won_restrict_per_stage/static/description/index.html
odoo/addons/crm_won_restrict_per_stage/tests/__init__.py
odoo/addons/crm_won_restrict_per_stage/tests/test_crm_lead.py
odoo/addons/crm_won_restrict_per_stage/views/crm_lead_views.xml
odoo/addons/crm_won_restrict_per_stage/views/crm_stage_views.xml
odoo_addon_crm_won_restrict_per_stage-18.0.1.0.0.3.dist-info/METADATA
odoo_addon_crm_won_restrict_per_stage-18.0.1.0.0.3.dist-info/WHEEL
odoo_addon_crm_won_restrict_per_stage-18.0.1.0.0.3.dist-info/top_level.txt
odoo_addon_crm_won_restrict_per_stage-18.0.1.0.0.3.dist-info/RECORD
